commune/README.md
commune/__init__.py
commune/cli/README.md
commune/cli/__init__.py
commune/cli/cli.py
commune/config.json
commune/key/README.md
commune/key/__init__.py
commune/key/key.py
commune/key/utils.py
commune/module.py
commune/server/README.md
commune/server/__init__.py
commune/server/client.py
commune/server/executor.py
commune/server/serializer/serializer.py
commune/server/serializer/types/bytes.py
commune/server/serializer/types/munch.py
commune/server/serializer/types/numpy.py
commune/server/serializer/types/pandas.py
commune/server/serializer/types/torch.py
commune/server/server.py
commune/utils/asyncio.py
commune/utils/log.py
commune/utils/misc.py
commune/utils/network.py
commune/utils/os.py
commune/utils/storage.py
commune/utils/thread.py
commai-0.0.2.dist-info/LICENCE
commai-0.0.2.dist-info/METADATA
commai-0.0.2.dist-info/WHEEL
commai-0.0.2.dist-info/entry_points.txt
commai-0.0.2.dist-info/RECORD
