Metadata-Version: 2.3
Name: commai
Version: 0.0.2
Summary: Gobal toolbox that allows you to connect, and verify your tools
License: MIT
Keywords: toolbox,verification,tools,global,machine learning,prompt,Artificial Intelligence,Large Language Models
Author: commune ai organization
Author-email: contact@communeai.org
Requires-Python: >=3.9,<=3.12
Classifier: License :: OSI Approved :: MIT License
Classifier: Programming Language :: Python :: 3
Classifier: Programming Language :: Python :: 3.9
Classifier: Programming Language :: Python :: 3.10
Classifier: Programming Language :: Python :: 3.11
Classifier: Programming Language :: Python :: 3.12
Requires-Dist: PyNaCl (>=1.5.0,<2.0.0)
Requires-Dist: aiofiles
Requires-Dist: aiohttp
Requires-Dist: asyncio
Requires-Dist: base58 (>=1.0.3)
Requires-Dist: certifi (>=2019.3.9)
Requires-Dist: ecdsa (>=0.17.0)
Requires-Dist: eth-keys (>=0.2.1)
Requires-Dist: eth_utils (>=1.3.0)
Requires-Dist: fastapi (==0.115.8)
Requires-Dist: idna (>=2.1.0)
Requires-Dist: loguru
Requires-Dist: msgpack_numpy
Requires-Dist: munch
Requires-Dist: nest_asyncio
Requires-Dist: netaddr
Requires-Dist: openai
Requires-Dist: pandas
Requires-Dist: paramiko
Requires-Dist: psutil
Requires-Dist: py-bip39-bindings (>=0.1.9)
Requires-Dist: py-ed25519-zebra-bindings (>=1.0)
Requires-Dist: py-sr25519-bindings (>=0.2.0)
Requires-Dist: pycryptodome (>=3.11.0)
Requires-Dist: pytest
Requires-Dist: pyyaml
Requires-Dist: requests (>=2.21.0)
Requires-Dist: retry
Requires-Dist: safetensors
Requires-Dist: scalecodec (>=1.2.10,<1.3)
Requires-Dist: sse-starlette
Requires-Dist: torch
Requires-Dist: twine
Requires-Dist: typer
Requires-Dist: uvicorn
Requires-Dist: websocket-client (>=0.57.0)
Requires-Dist: xxhash (>=1.3.0)
Project-URL: Homepage, https://communeai.org/
Project-URL: Repository, https://github.com/commune-ai/commune
